wvfreader.py
wvfreader-0.1.2.dist-info/METADATA
wvfreader-0.1.2.dist-info/RECORD
wvfreader-0.1.2.dist-info/WHEEL
wvfreader-0.1.2.dist-info/top_level.txt
