Metadata-Version: 2.1
Name: wvfreader
Version: 0.1.2
Summary: A package for working with Yokogowa oscilloscope files (WDF, WVF).
Home-page: https://github.com/pypa/wvfreader
Author: Devin Prescott
Author-email: devincprescott@gmail.com
License: UNKNOWN
Keywords: Yokogowa Oscilloscope WVF WDF
Platform: UNKNOWN
Classifier: Programming Language :: Python :: 3
Classifier: License :: OSI Approved :: GNU General Public License (GPL)
Classifier: License :: OSI Approved :: GNU General Public License v3 (GPLv3)
Classifier: Operating System :: OS Independent
